{
  "mcpServers": {
    "context7": {
      "command": "npx",
      "args": [
        "-y",
        "@upstash/context7-mcp"
      ],
      "env": {
        "DEFAULT_MINIMUM_TOKENS": ""
      }
    },
    "filesystem": {
      "command": "npx",
      "args": [
        "-y",
        "@modelcontextprotocol/server-filesystem",
        "C:\\Users\\IT\\Desktop",
        "C:\\Users\\IT\\Documents",
        "C:\\Users\\IT\\.gemini\\antigravity",
        "D:\\suzuzy_web_site",
        "C:\\Users\\IT\\.agent"
      ]
    },
    "sequential-thinking": {
      "command": "npx",
      "args": [
        "-y",
        "@modelcontextprotocol/server-sequential-thinking"
      ]
    },
    "memory": {
      "command": "npx",
      "args": [
        "-y",
        "@modelcontextprotocol/server-memory"
      ]
    },
    "supabase-mcp-server": {
      "command": "npx",
      "args": [
        "-y",
        "@supabase/mcp-server-supabase@latest",
        "--access-token",
        "sbp_d538e928f0ce54a39fd3bf440118f543b976ea7d"
      ],
      "env": {}
    }
  }
}